ecs_util/config.py
ecs_util/aws/parameter_store.py
ecs_util/aws/__init__.py
ecs_util/aws/ecs.py
ecs_util/aws/eventbridge.py
ecs_util/__init__.py
ecs_util/main.py
ecs_util/commands/create_task_definition.py
ecs_util/commands/exec.py
ecs_util/commands/db_snapshot.py
ecs_util/commands/deploy.py
ecs_util/commands/__init__.py
ecs_util/commands/migrate.py
ecs_util/commands/run.py
ecs_util-0.1.0.dist-info/WHEEL
ecs_util-0.1.0.dist-info/entry_points.txt
ecs_util-0.1.0.dist-info/METADATA
ecs_util-0.1.0.dist-info/RECORD
